{
  "items": [
    {
      "label": "First Name",
      "type": "text",
      "placeholder": "John"
    },
    {
      "label": "Last Name",
      "type": "text",
      "placeholder": "Smith"
    },
    {
      "label": "Email Address",
      "type": "email",
      "placeholder": "johnsmith@gmail.com",
      "for": "EmailReg"
    },
    {
      "label": "Username",
      "type": "text",
      "placeholder": "johnsmith",
      "autocomplete": "username"
    },
    {
      "label": "Password",
      "type": "password",
      "for": "PasswordReg",
      "placeholder": "Enter your password",
      "autocomplete": "new-password"
    },
    {
      "label": "Password Verification",
      "type": "password",
      "placeholder": "Re-enter your password",
      "for": "PasswordVerification",
      "autocomplete": "new-password"
    },
    {
      "label": "Title",
      "type": "text",
      "placeholder": "Title"
    },
    {
      "label": "Workout Date",
      "type": "date"
    },
    {
      "label": "Calories",
      "type": "number",
      "for": "Calories"
    },
    {
      "label": "Duration in Minutes",
      "type": "number",
      "for": "Duration"
    },
    {
      "label": "Distance in Feet",
      "type": "number",
      "for": "Distance"
    },
    {
      "label": "Location",
      "type": "text"
    },
    {
      "label": "Picture",
      "type": "text"
    },
    {
      "label": "Email Address",
      "type": "email",
      "placeholder": "Email Address",
      "for": "EmailLogin",
      "autocomplete": "email"
    },
    {
      "label": "Password",
      "type": "password",
      "for": "PasswordLogin",
      "placeholder": "Enter your password",
      "autocomplete": "current-password"
    }
  ]
}